vgs/__init__.py
vgs/aliases_api.py
vgs/base_api.py
vgs/configuration.py
vgs/exceptions.py
vgs/functions_api.py
vgs/certs/__init__.py
vgs/certs/vgs-proxy-dev.pem
vgs/certs/vgs-proxy-live.pem
vgs/certs/vgs-proxy-sandbox.pem
vgs/control_plane/__init__.py
vgs/control_plane/apis/__init__.py
vgs/control_plane/apis/account_management.py
vgs/control_plane/apis/vault_management.py
vgs/control_plane/clients/__init__.py
vgs/control_plane/clients/organizations.py
vgs/control_plane/clients/vaults.py
vgs/sdk/__init__.py
vgs/sdk/account_mgmt.py
vgs/sdk/accounts_api.py
vgs/sdk/auth_api.py
vgs/sdk/errors.py
vgs/sdk/routes.py
vgs/sdk/serializers.py
vgs/sdk/utils.py
vgs/sdk/vault_mgmt.py
vgs/sdk/vaults_api.py
vgs_api_client/__init__.py
vgs_api_client/api_client.py
vgs_api_client/configuration.py
vgs_api_client/exceptions.py
vgs_api_client/model_utils.py
vgs_api_client/rest.py
vgs_api_client/api/__init__.py
vgs_api_client/api/aliases_api.py
vgs_api_client/apis/__init__.py
vgs_api_client/model/__init__.py
vgs_api_client/model/alias_dto.py
vgs_api_client/model/alias_format.py
vgs_api_client/model/api_error.py
vgs_api_client/model/batch_aliases_request.py
vgs_api_client/model/create_aliases_request.py
vgs_api_client/model/create_aliases_request_new.py
vgs_api_client/model/create_aliases_request_reference.py
vgs_api_client/model/inline_response200.py
vgs_api_client/model/inline_response2001.py
vgs_api_client/model/inline_response201.py
vgs_api_client/model/inline_response_default.py
vgs_api_client/model/revealed_data.py
vgs_api_client/model/update_alias_request.py
vgs_api_client/model/update_alias_request_data.py
vgs_api_client/models/__init__.py
vgs_api_client-0.0.51.dist-info/LICENSE
vgs_api_client-0.0.51.dist-info/METADATA
vgs_api_client-0.0.51.dist-info/WHEEL
vgs_api_client-0.0.51.dist-info/top_level.txt
vgs_api_client-0.0.51.dist-info/RECORD
